{
  "_updated": "2026-03-21",
  "_schema": "1.0",

  "franchise": "The Witcher",
  "id": "witcher",
  "icon": "⚔️",
  "color": "#c0392b",
  "description": "Andrzej Sapkowski's dark fantasy saga about Geralt of Rivia, a mutant monster-hunter for hire navigating a morally grey world of humans, monsters, and politics. Born as Polish short stories in 1986, the franchise exploded globally through CD Projekt Red's acclaimed RPG trilogy — particularly The Witcher 3 (2015), one of the greatest games ever made.",

  "media": [

    {
      "title": "The Last Wish (short story collection)",
      "type": "book",
      "year": 1993,
      "platform": null,
      "volumes": 1,
      "author": "Andrzej Sapkowski",
      "rating": null,
      "status": "backlog",
      "description": "The foundational short story collection. Introduces Geralt, Yennefer, Dandelion. First English edition 2007. Stories include The Witcher, A Grain of Truth, The Lesser Evil, A Matter of Price, and The Last Wish.",
      "notes": "Start here. The Netflix S1 adapts most of this.",
      "canon": true
    },

    {
      "title": "Sword of Destiny (short story collection)",
      "type": "book",
      "year": 1992,
      "platform": null,
      "volumes": 1,
      "author": "Andrzej Sapkowski",
      "rating": null,
      "status": "backlog",
      "description": "Second short story collection. Introduces Ciri. Published before The Last Wish but set later. First English edition 2015.",
      "notes": "Read after The Last Wish. Introduces the Child Surprise / Ciri storyline.",
      "canon": true
    },

    {
      "title": "Blood of Elves",
      "type": "book",
      "year": 1994,
      "platform": null,
      "volumes": 1,
      "author": "Andrzej Sapkowski",
      "rating": null,
      "status": "backlog",
      "description": "First novel in the Witcher Saga. Geralt and Ciri travel together as the world descends into war. Sets up the full saga.",
      "notes": "Novel 1 of 5 in the Saga.",
      "canon": true
    },

    {
      "title": "Time of Contempt",
      "type": "book",
      "year": 1995,
      "platform": null,
      "volumes": 1,
      "author": "Andrzej Sapkowski",
      "rating": null,
      "status": "backlog",
      "description": "The Nilfgaard invasion escalates. Ciri separated from Geralt. Major political and magical upheaval.",
      "notes": "Novel 2 of 5.",
      "canon": true
    },

    {
      "title": "Baptism of Fire",
      "type": "book",
      "year": 1996,
      "platform": null,
      "volumes": 1,
      "author": "Andrzej Sapkowski",
      "rating": null,
      "status": "backlog",
      "description": "Geralt assembles a Hansa and marches south to find Ciri. Road-trip saga across a war-torn Continent.",
      "notes": "Novel 3 of 5.",
      "canon": true
    },

    {
      "title": "The Tower of the Swallow",
      "type": "book",
      "year": 1997,
      "platform": null,
      "volumes": 1,
      "author": "Andrzej Sapkowski",
      "rating": null,
      "status": "backlog",
      "description": "Ciri on the run; Geralt closing in. The saga's emotional peak.",
      "notes": "Novel 4 of 5.",
      "canon": true
    },

    {
      "title": "The Lady of the Lake",
      "type": "book",
      "year": 1999,
      "platform": null,
      "volumes": 1,
      "author": "Andrzej Sapkowski",
      "rating": null,
      "status": "backlog",
      "description": "The Saga conclusion. Ciri's destiny fulfilled. CDPR's games pick up roughly five years after this ending.",
      "notes": "Novel 5 of 5. End of the original Geralt saga.",
      "canon": true
    },

    {
      "title": "Season of Storms",
      "type": "book",
      "year": 2013,
      "platform": null,
      "volumes": 1,
      "author": "Andrzej Sapkowski",
      "rating": null,
      "status": "backlog",
      "description": "Standalone prequel novel — Geralt's swords are stolen. Set chronologically before The Last Wish events but written 14 years later. The Witcher 3 Blood and Wine draws from it.",
      "notes": "Standalone — read anytime after The Last Wish.",
      "canon": true
    },

    {
      "title": "Crossroads of Ravens",
      "type": "book",
      "year": 2024,
      "platform": null,
      "volumes": 1,
      "author": "Andrzej Sapkowski",
      "rating": null,
      "status": "backlog",
      "description": "Newest prequel novel (2024). Set before Blood of Elves. CDPR has hinted at incorporating elements into The Witcher 4.",
      "notes": "Newest Sapkowski Witcher book. International release late 2025.",
      "canon": true
    },

    {
      "title": "The Hexer (Wiedźmin) — Film",
      "type": "movie",
      "year": 2001,
      "platform": null,
      "rating": null,
      "status": "backlog",
      "description": "Polish theatrical film compiled from unreleased TV series footage. Directed by Marek Brodzki. Michał Żebrowski as Geralt. Famously incoherent — a 2-hour edit of what was meant to be 13 episodes. Polish-only release.",
      "notes": "Non-canon to CDPR or Netflix. Sapkowski himself criticized it. Historical curiosity only.",
      "canon": false
    },

    {
      "title": "The Hexer (Wiedźmin) — TV Series",
      "type": "tv",
      "year": 2002,
      "platform": null,
      "episodes": 13,
      "seasons": 1,
      "network": "TVP (Poland)",
      "rating": null,
      "status": "backlog",
      "description": "Polish TV series. 13 episodes. More coherent than the film, but still critically panned and canceled after one season. Covers Geralt's childhood through early adventures. Never officially released internationally.",
      "notes": "Polish-language only. No international distribution. Non-canon to games/Netflix. Historical curiosity.",
      "canon": false
    },

    {
      "title": "The Witcher (Metropolis Software) — CANCELED",
      "type": "game",
      "year": 1997,
      "platform": ["PC"],
      "developer": "Metropolis Software",
      "rating": null,
      "status": "n/a",
      "description": "A Witcher game was in development at Metropolis Software from 1996–1997 before being abandoned. The game's director Adrian Chmielarz actually coined the English word 'witcher' during this project. Never released.",
      "notes": "CANCELED. Only historically relevant — this is where the word 'witcher' comes from in English.",
      "canon": false
    },

    {
      "title": "The Witcher",
      "type": "game",
      "year": 2007,
      "platform": ["PC"],
      "developer": "CD Projekt Red",
      "rating": null,
      "status": "backlog",
      "description": "Geralt awakes with amnesia in a world rebuilding after the Nilfgaard wars. He hunts Salamandra, a criminal syndicate that stole witcher secrets. Unconventional combo-click combat. Enhanced Edition (2008) is the version to play.",
      "notes": "PC only (GoG). Enhanced Edition recommended. ~40-50 hours. CDPR's first game.",
      "canon": true
    },

    {
      "title": "The Witcher: Rise of the White Wolf — CANCELED",
      "type": "game",
      "year": 2009,
      "platform": ["PS3", "Xbox360"],
      "developer": "CD Projekt Red",
      "rating": null,
      "status": "n/a",
      "description": "Planned console port of The Witcher 1 with a rebuilt engine and new combat system. Canceled in spring 2009 due to publisher issues with Atari. Never released.",
      "notes": "CANCELED. Would have been the first console Witcher game.",
      "canon": false
    },

    {
      "title": "The Witcher: Crimson Trail",
      "type": "game",
      "year": 2007,
      "platform": ["Mobile (J2ME)"],
      "developer": "Breakpoint / Hands-On Mobile",
      "rating": null,
      "status": "n/a",
      "description": "Side-scrolling hack-and-slash mobile game for Java feature phones, released alongside the original Witcher PC game. Young Geralt hunting monsters. Considers a prequel. Abandonware now — the official site no longer exists.",
      "notes": "DEFUNCT. J2ME feature phone era. Can be found on abandonware sites. Not playable on modern smartphones.",
      "canon": false
    },

    {
      "title": "The Witcher: Versus",
      "type": "game",
      "year": 2008,
      "platform": ["Browser (Flash)"],
      "developer": "one2tribe / CD Projekt Red",
      "rating": null,
      "status": "n/a",
      "description": "Flash-based browser PvP fighting game. Three character classes: Witcher, Sorceress, Frightener. Tied to the thewitcher.com forum accounts. Shut down when Flash died.",
      "notes": "DEFUNCT. Flash-based. Dead as of Flash EOL (2020). Tie-in to the original game's community.",
      "canon": false
    },

    {
      "title": "The Witcher 2: Assassins of Kings",
      "type": "game",
      "year": 2011,
      "platform": ["PC", "Xbox360"],
      "developer": "CD Projekt Red",
      "rating": null,
      "status": "backlog",
      "description": "Geralt is framed for regicide and must clear his name while navigating a brutal war of succession. Entirely different Chapter 2 depending on a single timed decision. Stunning for its era. Enhanced Edition (2012) on PC; Xbox 360 version (2012) requires streaming via Sunshine.",
      "notes": "PC or Xbox 360. Chapter 2 branches completely based on one choice in Ch.1. ~30-40 hours.",
      "canon": true
    },

    {
      "title": "The Witcher Adventure Game",
      "type": "game",
      "year": 2014,
      "platform": ["PC", "Mobile (iOS/Android)"],
      "developer": "CD Projekt Red",
      "rating": null,
      "status": "backlog",
      "description": "Digital adaptation of the physical board game. Up to 4 players as Geralt, Triss, Yarpen, or Dandelion. Quest-based adventure game. Available on iOS and Android.",
      "notes": "Still available on mobile. Casual — good for series fans, not required.",
      "canon": false
    },

    {
      "title": "The Witcher Battle Arena",
      "type": "game",
      "year": 2014,
      "platform": ["Mobile (iOS/Android/Windows Phone)"],
      "developer": "CD Projekt Red / Fuero Games",
      "rating": null,
      "status": "n/a",
      "description": "Free-to-play MOBA for mobile. 6-player capture-and-hold battles with 8 Witcher-universe heroes. Shut down December 31, 2015 after just over a year — servers closed permanently.",
      "notes": "DEFUNCT. Servers shut Dec 31 2015. MOBA trend chaser that didn't survive.",
      "canon": false
    },

    {
      "title": "The Witcher 3: Wild Hunt",
      "type": "game",
      "year": 2015,
      "platform": ["PC", "PS4", "XBO", "Switch", "PS5"],
      "developer": "CD Projekt Red",
      "rating": null,
      "status": "backlog",
      "description": "Geralt searches for Ciri as the Wild Hunt closes in. One of the greatest RPGs ever made. 100+ hours with both expansions. Next-Gen Edition (2022) is the version to play. Switch port playable but visually degraded.",
      "notes": "Play this. Next-Gen Edition on PC/PS5 recommended. Complete Edition includes Hearts of Stone + Blood and Wine DLCs.",
      "canon": true
    },

    {
      "title": "Hearts of Stone (DLC)",
      "type": "game",
      "year": 2015,
      "platform": ["PC", "PS4", "XBO", "Switch", "PS5"],
      "developer": "CD Projekt Red",
      "rating": null,
      "status": "backlog",
      "description": "Witcher 3 expansion. Geralt bound in a cursed contract with an immortal trickster, Gaunter O'Dimm. ~10-15 hours. Often considered the best Witcher story ever written.",
      "notes": "Requires TW3 base game. Play after the main story or mid-playthrough.",
      "canon": true
    },

    {
      "title": "Blood and Wine (DLC)",
      "type": "game",
      "year": 2016,
      "platform": ["PC", "PS4", "XBO", "Switch", "PS5"],
      "developer": "CD Projekt Red",
      "rating": null,
      "status": "backlog",
      "description": "Witcher 3 expansion. Toussaint — a sun-drenched vineyard land hiding a monster of legend. Geralt's final chapter. Enormous — 20+ hours, essentially a full game. Perfect ending for the Geralt era.",
      "notes": "Play last. Geralt's send-off. Draws heavily from Season of Storms novel.",
      "canon": true
    },

    {
      "title": "GWENT: The Witcher Card Game",
      "type": "game",
      "year": 2018,
      "platform": ["PC", "Mobile (iOS/Android)"],
      "developer": "CD Projekt Red",
      "rating": null,
      "status": "backlog",
      "description": "Standalone version of the card game from Witcher 3. Free-to-play digital CCG. PC and mobile. Still live as of 2026. The mobile version launched in 2019.",
      "notes": "Free-to-play. Still active on iOS/Android and GOG/Steam.",
      "canon": false
    },

    {
      "title": "Thronebreaker: The Witcher Tales",
      "type": "game",
      "year": 2018,
      "platform": ["PC", "Switch", "PS4", "XBO", "Mobile (iOS/Android)"],
      "developer": "CD Projekt Red",
      "rating": null,
      "status": "backlog",
      "description": "Single-player RPG using GWENT mechanics. Queen Meve of Lyria faces Nilfgaard invasion. 30-hour story that serves as a GWENT prequel. Mobile version released 2020-2021.",
      "notes": "Available on iOS and Android. Premium paid title — no F2P. Standalone story, no TW3 knowledge needed.",
      "canon": true
    },

    {
      "title": "The Witcher: Nightmare of the Wolf",
      "type": "movie",
      "year": 2021,
      "platform": null,
      "rating": null,
      "status": "backlog",
      "description": "Netflix animated film. Origin story of Vesemir — the oldest witcher of Kaer Morhen. Covers the catastrophe that wiped out most witchers. Studio Mir animation (same as Avatar: The Legend of Korra). Canon to Netflix continuity.",
      "notes": "Netflix. Watch before TW series Season 2 for maximum impact. Voiced by Theo James (Vesemir).",
      "canon": true
    },

    {
      "title": "The Witcher: Monster Slayer",
      "type": "game",
      "year": 2021,
      "platform": ["Mobile (iOS/Android)"],
      "developer": "Spokko / CD Projekt",
      "rating": null,
      "status": "n/a",
      "description": "Augmented-reality location-based RPG (Pokémon GO-style). Set before Geralt's era — players become new witchers hunting monsters in the real world. Reached 500k downloads in 3 days; over 100 million monsters slain before shutdown. Shut down June 30, 2023.",
      "notes": "DEFUNCT. Servers shut June 30 2023. AR game for iOS/Android — no longer downloadable.",
      "canon": false
    },

    {
      "title": "The Witcher: Roach Race",
      "type": "game",
      "year": 2022,
      "platform": ["Mobile (iOS/Android)"],
      "developer": "CD Projekt Red / Crunching Koalas",
      "rating": null,
      "status": "backlog",
      "description": "Free mobile endless runner / platformer. Play as Roach, Geralt's horse. Five levels. Also embedded as an arcade minigame in Cyberpunk 2077 Patch 1.6. Silly fan-service spinoff.",
      "notes": "Still available free on iOS/Android. Lighthearted. Also playable in Cyberpunk 2077.",
      "canon": false
    },

    {
      "title": "The Witcher (Netflix) — Season 1",
      "type": "tv",
      "year": 2019,
      "platform": null,
      "episodes": 8,
      "seasons": 1,
      "network": "Netflix",
      "rating": null,
      "status": "backlog",
      "description": "Henry Cavill as Geralt. Adapts The Last Wish and Sword of Destiny short stories across three non-linear timelines (Geralt/Yennefer/Ciri). Famously confusing on first watch — the timelines converge at episode 6.",
      "notes": "Netflix. Season 1 uses non-linear storytelling — all three arcs are in different time periods simultaneously.",
      "canon": true
    },

    {
      "title": "The Witcher (Netflix) — Season 2",
      "type": "tv",
      "year": 2021,
      "platform": null,
      "episodes": 8,
      "seasons": 1,
      "network": "Netflix",
      "rating": null,
      "status": "backlog",
      "description": "Linear timeline. Geralt brings Ciri to Kaer Morhen. Adapts loosely from Blood of Elves. Received much better than Season 1 for coherent structure.",
      "notes": "Netflix. Watch Nightmare of the Wolf before this for full Vesemir/Kaer Morhen context.",
      "canon": true
    },

    {
      "title": "The Witcher: Blood Origin",
      "type": "tv",
      "year": 2022,
      "platform": null,
      "episodes": 4,
      "seasons": 1,
      "network": "Netflix",
      "rating": null,
      "status": "backlog",
      "description": "Netflix limited series. 1200 years before Geralt. Origin of the first Witcher, the Conjunction of Spheres, and the first elven mages. Mixed reception; considered the weakest Netflix Witcher entry.",
      "notes": "Netflix. 4 episodes. Chronologically first in the Netflix universe. Optional — standalone world-building.",
      "canon": true
    },

    {
      "title": "The Witcher (Netflix) — Season 3",
      "type": "tv",
      "year": 2023,
      "platform": null,
      "episodes": 8,
      "seasons": 1,
      "network": "Netflix",
      "rating": null,
      "status": "backlog",
      "description": "Henry Cavill's final season as Geralt. Adapts Time of Contempt. Released in two parts (Vol.1: June, Vol.2: July 2023). Cavill announced departure mid-season rollout, creating a bittersweet finale.",
      "notes": "Netflix. Henry Cavill's last season. Split release — 5 episodes then 3.",
      "canon": true
    },

    {
      "title": "The Witcher: Sirens of the Deep",
      "type": "movie",
      "year": 2025,
      "platform": null,
      "rating": null,
      "status": "backlog",
      "description": "Netflix animated film. Adapts 'A Little Sacrifice' from the Sword of Destiny collection — Geralt hired to investigate attacks on a coastal village by sea people. Doug Cockle (TW game series) voices Geralt. Animation by Kang Hei Chul.",
      "notes": "Netflix. Doug Cockle voices Geralt — same voice actor as the games. Set in the Netflix continuity.",
      "canon": true
    },

    {
      "title": "The Witcher (Netflix) — Season 4",
      "type": "tv",
      "year": 2025,
      "platform": null,
      "episodes": 8,
      "seasons": 1,
      "network": "Netflix",
      "rating": null,
      "status": "backlog",
      "description": "Liam Hemsworth replaces Henry Cavill as Geralt. Mixed reception largely driven by the recasting controversy. Continues the main Continent storyline.",
      "notes": "Netflix. Liam Hemsworth era begins. Cavill confirmed it was his choice to leave for Superman.",
      "canon": true
    },

    {
      "title": "The Rats: A Witcher Tale",
      "type": "movie",
      "year": 2025,
      "platform": null,
      "rating": null,
      "status": "backlog",
      "description": "Netflix animated spin-off film following The Rats — the gang of young outlaws Ciri runs with in the books. Quietly dropped on Netflix. Based on events from Tower of the Swallow.",
      "notes": "Netflix. Released quietly alongside Season 4 build-up.",
      "canon": true
    },

    {
      "title": "The Witcher (Netflix) — Season 5 (UPCOMING)",
      "type": "tv",
      "year": 2026,
      "platform": null,
      "episodes": null,
      "seasons": 1,
      "network": "Netflix",
      "rating": null,
      "status": "backlog",
      "description": "Confirmed final season of the Netflix Witcher series. Liam Hemsworth as Geralt. Will conclude the Netflix storyline.",
      "notes": "UPCOMING. Netflix has confirmed Season 5 will be the last.",
      "canon": true
    },

    {
      "title": "The Witcher 4 / Project Polaris (UPCOMING)",
      "type": "game",
      "year": 2027,
      "platform": ["PC", "PS5"],
      "developer": "CD Projekt Red",
      "rating": null,
      "status": "backlog",
      "description": "The Witcher IV — first in a new trilogy. Ciri as protagonist. Revealed at The Game Awards 2024 with cinematic trailer. Built on Unreal Engine 5. CDPR confirmed it will not launch before 2027.",
      "notes": "UPCOMING. No release date confirmed. Not before 2027 per CDPR earnings call March 2025.",
      "canon": true
    },

    {
      "title": "Project Sirius (UPCOMING — Spinoff)",
      "type": "game",
      "year": null,
      "platform": ["PC"],
      "developer": "The Molasses Flood (absorbed by CDPR April 2025)",
      "rating": null,
      "status": "backlog",
      "description": "Co-op/multiplayer Witcher spinoff with single-player campaign. Rebooted in early 2023. Developed by The Molasses Flood, now fully absorbed into CDPR. No release window known.",
      "notes": "UPCOMING. Development rebooted 2023. The Molasses Flood merged into CDPR April 2025.",
      "canon": false
    },

    {
      "title": "Canis Majoris / Witcher 1 Remake (UPCOMING)",
      "type": "game",
      "year": null,
      "platform": ["PC"],
      "developer": "Fool's Theory (supervised by CDPR)",
      "rating": null,
      "status": "backlog",
      "description": "Full remake of The Witcher (2007) in Unreal Engine 5, developed by Polish indie studio Fool's Theory under CDPR supervision. Still in concept phase as of early 2025.",
      "notes": "UPCOMING. Still early concept phase. Fool's Theory has Witcher 3 and BG3 veterans.",
      "canon": true
    },

    {
      "title": "The Witcher: House of Glass (Comic)",
      "type": "manga",
      "year": 2014,
      "platform": null,
      "volumes": 1,
      "rating": null,
      "status": "backlog",
      "description": "Dark Horse Comics. Original story by Paul Tobin. Geralt investigates a haunted manor in the forest. Set in the game continuity.",
      "notes": "Dark Horse. Game-universe canon. First of several Dark Horse arcs.",
      "canon": true
    },

    {
      "title": "The Witcher: Fox Children (Comic)",
      "type": "manga",
      "year": 2015,
      "platform": null,
      "volumes": 1,
      "rating": null,
      "status": "backlog",
      "description": "Dark Horse Comics. Adapts a chapter from Season of Storms. Geralt chases a mysterious creature through a swamp.",
      "notes": "Dark Horse. Adapts Season of Storms material.",
      "canon": true
    },

    {
      "title": "The Witcher: Curse of Crows (Comic)",
      "type": "manga",
      "year": 2016,
      "platform": null,
      "volumes": 1,
      "rating": null,
      "status": "backlog",
      "description": "Dark Horse Comics. Original story continuing from The Witcher 3. Ciri and Geralt face a vengeful witch.",
      "notes": "Dark Horse. Set after TW3.",
      "canon": true
    },

    {
      "title": "The Witcher: Of Flesh and Flame (Comic)",
      "type": "manga",
      "year": 2018,
      "platform": null,
      "volumes": 1,
      "rating": null,
      "status": "backlog",
      "description": "Dark Horse Comics. Geralt escorted on a desert caravan, uncovering a conspiracy. Original story.",
      "notes": "Dark Horse. Game-universe canon.",
      "canon": true
    },

    {
      "title": "The Witcher: Ronin (Manga)",
      "type": "manga",
      "year": 2022,
      "platform": null,
      "volumes": 1,
      "rating": null,
      "status": "backlog",
      "description": "Crowdfunded manga (Kickstarter, Sept 2021). Geralt in Feudal Japan fighting yokai instead of European monsters. Illustrated in manga style. Ships started in March 2022.",
      "notes": "Non-canon alternate-universe. Fun what-if. CDPR-endorsed.",
      "canon": false
    },

    {
      "title": "The Witcher: Wiedźmin (Polish Comics, 1993–1995)",
      "type": "manga",
      "year": 1993,
      "platform": null,
      "volumes": 5,
      "rating": null,
      "status": "backlog",
      "description": "Original Polish comic book series by Bogusław Polch (art) and Maciej Parowski (script). Released before the games, adapted short stories from The Last Wish. Available in Polish only; partial English fan-translations exist.",
      "notes": "Polish only. Based on Sapkowski's short stories. Historically significant as the first Witcher visual media.",
      "canon": true
    }

  ]
}
